demos/identification/hardening_rule.py
demos/identification/nonlinear_kinematic_hardening.py
demos/neural_network_models/hyperelastic_PANN.py
demos/neural_network_models/neural_GSM.py
demos/phenomenological_models/CamClay.py
demos/phenomenological_models/Green_viscoplasticity.py
demos/phenomenological_models/multisurface_plasticity.py
demos/quickstart/batched_computation.py
demos/quickstart/generate_performance_data.py
demos/quickstart/getting_started.py
demos/quickstart/material_parameters_batching.py
docs/remove_docstring.py
docs/_build/html/_downloads/cc81594d3e763f99bc7159ffac8729d4/generate_performance_data.py
docs/demos/identification/hardening_rule.py
docs/demos/identification/nonlinear_kinematic_hardening.py
docs/demos/neural_network_models/hyperelastic_PANN.py
docs/demos/neural_network_models/neural_GSM.py
docs/demos/phenomenological_models/CamClay.py
docs/demos/phenomenological_models/Green_viscoplasticity.py
docs/demos/phenomenological_models/multisurface_plasticity.py
docs/demos/quickstart/batched_computation.py
docs/demos/quickstart/generate_performance_data.py
docs/demos/quickstart/getting_started.py
docs/demos/quickstart/material_parameters_batching.py
jaxmat/__init__.py
jaxmat/loader.py
jaxmat/state.py
jaxmat/utils.py
jaxmat/materials/__init__.py
jaxmat/materials/behavior.py
jaxmat/materials/elasticity.py
jaxmat/materials/elastoplasticity.py
jaxmat/materials/fe_fp_elastoplasticity.py
jaxmat/materials/generalized_standard.py
jaxmat/materials/hyperelasticity.py
jaxmat/materials/plastic_surfaces.py
jaxmat/materials/viscoelasticity.py
jaxmat/materials/viscoplastic_flows.py
jaxmat/materials/viscoplasticity.py
jaxmat/nn/icnn.py
jaxmat/solvers/__init__.py
jaxmat/solvers/custom_newton.py
jaxmat/solvers/custom_optimistix_solvers.py
jaxmat/tensors/__init__.py
jaxmat/tensors/generic_tensors.py
jaxmat/tensors/linear_algebra.py
jaxmat/tensors/tensor_utils.py
jaxmat/tensors/utils.py
jaxmat-0.0.1.dist-info/licenses/LICENSE
sandbox/damage.py
sandbox/diff_aux.py
sandbox/elastoplasticity_extended.py
jaxmat-0.0.1.dist-info/METADATA
jaxmat-0.0.1.dist-info/WHEEL
jaxmat-0.0.1.dist-info/top_level.txt
jaxmat-0.0.1.dist-info/RECORD
