Metadata-Version: 2.4
Name: jaxmat
Version: 0.0.1
Summary: Automated material constitutive modeling in JAX
Author-email: Jeremy Bleyer <jeremy.bleyer@enpc.fr>, Paul Bouteiller <paul.bouteiller@cea.fr>
License: GNU GPLv3
Keywords: material science,machine learning,material modeling,solid mechanics,automatic differentiation
Requires-Python: >=3.10
License-File: LICENSE
Requires-Dist: jax>=0.6.1
Requires-Dist: optax
Requires-Dist: equinox
Requires-Dist: diffrax
Requires-Dist: optimistix
Requires-Dist: lineax
Provides-Extra: gpu
Requires-Dist: jax[cuda12]>=0.6.1; extra == "gpu"
Dynamic: license-file
